modelz_llm/__init__.py
modelz_llm/_version.py
modelz_llm/cli.py
modelz_llm/emb.py
modelz_llm/falcon_service.py
modelz_llm/log.py
modelz_llm/model.py
modelz_llm/mosec_service.py
modelz_llm/uds.py
modelz_llm/utils.py
modelz_llm-23.7.4.dist-info/METADATA
modelz_llm-23.7.4.dist-info/WHEEL
modelz_llm-23.7.4.dist-info/entry_points.txt
modelz_llm-23.7.4.dist-info/top_level.txt
modelz_llm-23.7.4.dist-info/RECORD
