Metadata-Version: 2.1
Name: modelz-llm
Version: 23.7.4
Summary: LLM unified service
Author-email: TensorChord <modelz@tensorchord.ai>
Project-URL: Homepage, https://github.com/tensorchord/modelz-llm
Classifier: Intended Audience :: Developers
Classifier: Topic :: Scientific/Engineering :: Artificial Intelligence
Requires-Python: >=3.8
Requires-Dist: llmspec
Requires-Dist: falcon (>=3)
Requires-Dist: uvicorn (>=0.22)
Requires-Dist: mosec (>0.6)
Provides-Extra: gpu
Requires-Dist: torch ; extra == 'gpu'
Requires-Dist: transformers ; extra == 'gpu'
Requires-Dist: sentencepiece ; extra == 'gpu'
Requires-Dist: accelerate ; extra == 'gpu'
Requires-Dist: cpm-kernels ; extra == 'gpu'
